sense_push/__init__.py
sense_push/common/__init__.py
sense_push/common/constants.py
sense_push/core/__init__.py
sense_push/core/consume.py
sense_push/core/data.py
sense_push/core/django_handler.py
sense_push/core/dumb_handler.py
sense_push/core/manager.py
sense_push/util/__init__.py
sense_push/util/utils.py
sense_push-0.1.18.dist-info/METADATA
sense_push-0.1.18.dist-info/WHEEL
sense_push-0.1.18.dist-info/top_level.txt
sense_push-0.1.18.dist-info/RECORD
