Metadata-Version: 2.1
Name: sense-push
Version: 0.1.18
Summary: sense push
Home-page: UNKNOWN
Author: kafka0102
Author-email: yujianjia@sensedeal.ai
License: BSD License
Platform: UNKNOWN
Classifier: Intended Audience :: Developers
Classifier: License :: OSI Approved :: BSD License
Classifier: Operating System :: OS Independent
Classifier: Programming Language :: Python
Classifier: Programming Language :: Python :: 3.6
Requires-Dist: sense-core (>=0.2.61)
Requires-Dist: django
